imea/__init__.py
imea/extract.py
imea/measure_2d/__init__.py
imea/measure_2d/macro.py
imea/measure_2d/meso.py
imea/measure_2d/micro.py
imea/measure_2d/statistical_length.py
imea/measure_2d/utils.py
imea/measure_3d/__init__.py
imea/measure_3d/macro.py
imea/measure_3d/utils.py
imea/tools/__init__.py
imea/tools/draw.py
imea/tools/preprocess.py
imea/tools/project.py
imea/tools/rotate.py
imea-0.3.5.dist-info/LICENSE
imea-0.3.5.dist-info/METADATA
imea-0.3.5.dist-info/WHEEL
imea-0.3.5.dist-info/top_level.txt
imea-0.3.5.dist-info/RECORD
