Metadata-Version: 2.1
Name: imea
Version: 0.3.5
Summary: imea is an open source Python package for extracting 2D and 3D shape measurements from images.
Home-page: https://git.rwth-aachen.de/ants/sensorlab/imea
Author: Nils Kroell
Author-email: nils.kroell@ants.rwth-aachen.de
License: MIT
Classifier: Development Status :: 5 - Production/Stable
Classifier: License :: OSI Approved :: MIT License
Classifier: Programming Language :: Python
Classifier: Programming Language :: Python :: 3.7
Classifier: Programming Language :: Python :: 3.8
Classifier: Topic :: Software Development :: Libraries
Classifier: Topic :: Software Development :: Libraries :: Python Modules
Classifier: Intended Audience :: Science/Research
Classifier: Intended Audience :: Developers
Classifier: Intended Audience :: Developers
Classifier: Topic :: Scientific/Engineering
Classifier: Topic :: Scientific/Engineering :: Image Processing
Requires-Python: >=3.7
License-File: LICENSE
Requires-Dist: numpy >=1.18
Requires-Dist: scipy >=1.10
Requires-Dist: scikit-image >=0.16
Requires-Dist: opencv-python >=4.5
Requires-Dist: pandas >=1.0.5
